cardspy/__init__.py
cardspy/card.py
cardspy/deck.py
cardspy/py.typed
cardspy/rank.py
cardspy/suit.py
cardspy-2.4.dist-info/METADATA
cardspy-2.4.dist-info/WHEEL
cardspy-2.4.dist-info/RECORD
