Metadata-Version: 2.3
Name: cardspy
Version: 2.4
Summary: Functionalities for playing cards
Author: bd.noads@gmail.com
Requires-Python: >=3.10
Classifier: Programming Language :: Python :: 3
Classifier: Programming Language :: Python :: 3.10
Classifier: Programming Language :: Python :: 3.11
Classifier: Programming Language :: Python :: 3.12
Classifier: Programming Language :: Python :: 3.13
Requires-Dist: mypy (>=1.15.0,<2.0.0)
